youdao_dict/__init__.py
youdao_dict/utils.py
youdao_dict/youdao.py
youdao_dict/spellcheck/__init__.py
youdao_dict/spellcheck/big.txt
youdao_dict/spellcheck/spell-testset1.txt
youdao_dict/spellcheck/spell-testset2.txt
youdao_dict/spellcheck/spell.py
youdao_dict-1.0.5.dist-info/LICENSE
youdao_dict-1.0.5.dist-info/METADATA
youdao_dict-1.0.5.dist-info/WHEEL
youdao_dict-1.0.5.dist-info/entry_points.txt
youdao_dict-1.0.5.dist-info/top_level.txt
youdao_dict-1.0.5.dist-info/RECORD
