Metadata-Version: 2.1
Name: youdao-dict
Version: 1.0.5
Summary: Query Youdao Dictionary in Command Line
Home-page: https://github.com/WangXin93/youdao_dict
Author: Xin Wang
Author-email: wangxin19930411@163.com
Classifier: Programming Language :: Python :: 3
Classifier: License :: OSI Approved :: MIT License
Classifier: Operating System :: OS Independent
License-File: LICENSE
Requires-Dist: requests (>=2.19.1)
Requires-Dist: lxml (>=4.1.0)
Requires-Dist: python-vlc (>=3.0.101)
Requires-Dist: pyttsx3 (>=2.9.0)
